<?xml version="1.0" ?>
<annotation>
  <folder>/home/firefly/Documents/1205/Annotations</folder>
  <filename>image_0416013722_3.png</filename>
  <size>
    <width>1280</width>
    <height>720</height>
    <depth>3</depth>
  </size>
  <source>
    <database>https://github.com/CVHub520/X-AnyLabeling</database>
  </source>
  <object>
    <name>black</name>
    <pose>Unspecified</pose>
    <truncated>0</truncated>
    <occluded>0</occluded>
    <difficult>0</difficult>
    <bndbox>
      <xmin>811</xmin>
      <ymin>148</ymin>
      <xmax>868</xmax>
      <ymax>210</ymax>
    </bndbox>
  </object>
  <object>
    <name>blue</name>
    <pose>Unspecified</pose>
    <truncated>0</truncated>
    <occluded>0</occluded>
    <difficult>0</difficult>
    <bndbox>
      <xmin>522</xmin>
      <ymin>131</ymin>
      <xmax>573</xmax>
      <ymax>188</ymax>
    </bndbox>
  </object>
  <object>
    <name>blue</name>
    <pose>Unspecified</pose>
    <truncated>0</truncated>
    <occluded>0</occluded>
    <difficult>0</difficult>
    <bndbox>
      <xmin>692</xmin>
      <ymin>104</ymin>
      <xmax>738</xmax>
      <ymax>153</ymax>
    </bndbox>
  </object>
  <object>
    <name>yellow</name>
    <pose>Unspecified</pose>
    <truncated>0</truncated>
    <occluded>0</occluded>
    <difficult>0</difficult>
    <bndbox>
      <xmin>362</xmin>
      <ymin>144</ymin>
      <xmax>421</xmax>
      <ymax>205</ymax>
    </bndbox>
  </object>
  <object>
    <name>black</name>
    <pose>Unspecified</pose>
    <truncated>0</truncated>
    <occluded>0</occluded>
    <difficult>0</difficult>
    <bndbox>
      <xmin>575</xmin>
      <ymin>129</ymin>
      <xmax>627</xmax>
      <ymax>184</ymax>
    </bndbox>
  </object>
  <object>
    <name>blue</name>
    <pose>Unspecified</pose>
    <truncated>0</truncated>
    <occluded>0</occluded>
    <difficult>0</difficult>
    <bndbox>
      <xmin>600</xmin>
      <ymin>588</ymin>
      <xmax>756</xmax>
      <ymax>718</ymax>
    </bndbox>
  </object>
</annotation>
