<?xml version="1.0" ?>
<annotation>
  <folder>/home/firefly/Documents/1205/Annotations</folder>
  <filename>image_0416013643_20.png</filename>
  <size>
    <width>1280</width>
    <height>720</height>
    <depth>3</depth>
  </size>
  <source>
    <database>https://github.com/CVHub520/X-AnyLabeling</database>
  </source>
  <object>
    <name>black</name>
    <pose>Unspecified</pose>
    <truncated>0</truncated>
    <occluded>0</occluded>
    <difficult>0</difficult>
    <bndbox>
      <xmin>541</xmin>
      <ymin>149</ymin>
      <xmax>599</xmax>
      <ymax>215</ymax>
    </bndbox>
  </object>
  <object>
    <name>yellow</name>
    <pose>Unspecified</pose>
    <truncated>0</truncated>
    <occluded>0</occluded>
    <difficult>0</difficult>
    <bndbox>
      <xmin>272</xmin>
      <ymin>476</ymin>
      <xmax>423</xmax>
      <ymax>622</ymax>
    </bndbox>
  </object>
  <object>
    <name>blue</name>
    <pose>Unspecified</pose>
    <truncated>0</truncated>
    <occluded>0</occluded>
    <difficult>0</difficult>
    <bndbox>
      <xmin>0</xmin>
      <ymin>559</ymin>
      <xmax>97</xmax>
      <ymax>692</ymax>
    </bndbox>
  </object>
  <object>
    <name>blue</name>
    <pose>Unspecified</pose>
    <truncated>0</truncated>
    <occluded>0</occluded>
    <difficult>0</difficult>
    <bndbox>
      <xmin>162</xmin>
      <ymin>80</ymin>
      <xmax>212</xmax>
      <ymax>125</ymax>
    </bndbox>
  </object>
  <object>
    <name>red</name>
    <pose>Unspecified</pose>
    <truncated>0</truncated>
    <occluded>0</occluded>
    <difficult>0</difficult>
    <bndbox>
      <xmin>305</xmin>
      <ymin>104</ymin>
      <xmax>361</xmax>
      <ymax>158</ymax>
    </bndbox>
  </object>
  <object>
    <name>black</name>
    <pose>Unspecified</pose>
    <truncated>0</truncated>
    <occluded>0</occluded>
    <difficult>0</difficult>
    <bndbox>
      <xmin>641</xmin>
      <ymin>164</ymin>
      <xmax>698</xmax>
      <ymax>218</ymax>
    </bndbox>
  </object>
</annotation>
