<annotation>
	<folder>images</folder>
	<filename>image_0416013706_7.png</filename>
	<path>/home/firefly/Documents/1205/images/image_0416013706_7.png</path>
	<source>
		<database>Unknown</database>
	</source>
	<size>
		<width>1280</width>
		<height>720</height>
		<depth>3</depth>
	</size>
	<segmented>0</segmented>
	<object>
		<name>black</name>
		<pose>Unspecified</pose>
		<truncated>0</truncated>
		<difficult>0</difficult>
		<bndbox>
			<xmin>655</xmin>
			<ymin>346</ymin>
			<xmax>757</xmax>
			<ymax>464</ymax>
		</bndbox>
	</object>
	<object>
		<name>blue</name>
		<pose>Unspecified</pose>
		<truncated>0</truncated>
		<difficult>0</difficult>
		<bndbox>
			<xmin>553</xmin>
			<ymin>276</ymin>
			<xmax>639</xmax>
			<ymax>362</ymax>
		</bndbox>
	</object>
	<object>
		<name>blue</name>
		<pose>Unspecified</pose>
		<truncated>0</truncated>
		<difficult>0</difficult>
		<bndbox>
			<xmin>1086</xmin>
			<ymin>420</ymin>
			<xmax>1216</xmax>
			<ymax>543</ymax>
		</bndbox>
	</object>
	<object>
		<name>black</name>
		<pose>Unspecified</pose>
		<truncated>0</truncated>
		<difficult>0</difficult>
		<bndbox>
			<xmin>1109</xmin>
			<ymin>96</ymin>
			<xmax>1157</xmax>
			<ymax>149</ymax>
		</bndbox>
	</object>
	<object>
		<name>yellow</name>
		<pose>Unspecified</pose>
		<truncated>0</truncated>
		<difficult>0</difficult>
		<bndbox>
			<xmin>1212</xmin>
			<ymin>101</ymin>
			<xmax>1249</xmax>
			<ymax>143</ymax>
		</bndbox>
	</object>
</annotation>
