{
  "version": "2.5.3",
  "flags": {},
  "shapes": [
    {
      "label": "black",
      "score": 0.9419212341308594,
      "points": [
        [
          920.8704223632812,
          218.61865234375
        ],
        [
          1003.2869262695312,
          218.61865234375
        ],
        [
          1003.2869262695312,
          302.15966796875
        ],
        [
          920.8704223632812,
          302.15966796875
        ]
      ],
      "group_id": null,
      "description": null,
      "difficult": false,
      "shape_type": "rectangle",
      "flags": {},
      "attributes": {},
      "kie_linking": []
    },
    {
      "label": "red",
      "score": 0.9410673379898071,
      "points": [
        [
          632.33984375,
          171.579345703125
        ],
        [
          695.83056640625,
          171.579345703125
        ],
        [
          695.83056640625,
          236.4764404296875
        ],
        [
          632.33984375,
          236.4764404296875
        ]
      ],
      "group_id": null,
      "description": null,
      "difficult": false,
      "shape_type": "rectangle",
      "flags": {},
      "attributes": {},
      "kie_linking": []
    },
    {
      "label": "black",
      "score": 0.9383437037467957,
      "points": [
        [
          399.3819580078125,
          193.4656982421875
        ],
        [
          474.33544921875,
          193.4656982421875
        ],
        [
          474.33544921875,
          268.7137451171875
        ],
        [
          399.3819580078125,
          268.7137451171875
        ]
      ],
      "group_id": null,
      "description": null,
      "difficult": false,
      "shape_type": "rectangle",
      "flags": {},
      "attributes": {},
      "kie_linking": []
    },
    {
      "label": "blue",
      "score": 0.9311826229095459,
      "points": [
        [
          652.3154296875,
          492.66650390625
        ],
        [
          791.94873046875,
          492.66650390625
        ],
        [
          791.94873046875,
          643.614501953125
        ],
        [
          652.3154296875,
          643.614501953125
        ]
      ],
      "group_id": null,
      "description": null,
      "difficult": false,
      "shape_type": "rectangle",
      "flags": {},
      "attributes": {},
      "kie_linking": []
    },
    {
      "label": "blue",
      "score": 0.9282742738723755,
      "points": [
        [
          61.26123809814453,
          413.60845947265625
        ],
        [
          198.376220703125,
          413.60845947265625
        ],
        [
          198.376220703125,
          542.9730834960938
        ],
        [
          61.26123809814453,
          542.9730834960938
        ]
      ],
      "group_id": null,
      "description": null,
      "difficult": false,
      "shape_type": "rectangle",
      "flags": {},
      "attributes": {},
      "kie_linking": []
    },
    {
      "label": "yellow",
      "score": 0.9234437942504883,
      "points": [
        [
          240.6229248046875,
          215.13409423828125
        ],
        [
          324.14166259765625,
          215.13409423828125
        ],
        [
          324.14166259765625,
          294.36163330078125
        ],
        [
          240.6229248046875,
          294.36163330078125
        ]
      ],
      "group_id": null,
      "description": null,
      "difficult": false,
      "shape_type": "rectangle",
      "flags": {},
      "attributes": {},
      "kie_linking": []
    },
    {
      "label": "black",
      "score": 0.9230154752731323,
      "points": [
        [
          505.8601989746094,
          217.3182373046875
        ],
        [
          579.3568115234375,
          217.3182373046875
        ],
        [
          579.3568115234375,
          293.2132568359375
        ],
        [
          505.8601989746094,
          293.2132568359375
        ]
      ],
      "group_id": null,
      "description": null,
      "difficult": false,
      "shape_type": "rectangle",
      "flags": {},
      "attributes": {},
      "kie_linking": []
    },
    {
      "label": "blue",
      "score": 0.9079436659812927,
      "points": [
        [
          544.7901611328125,
          166.71856689453125
        ],
        [
          609.51806640625,
          166.71856689453125
        ],
        [
          609.51806640625,
          231.56390380859375
        ],
        [
          544.7901611328125,
          231.56390380859375
        ]
      ],
      "group_id": null,
      "description": null,
      "difficult": false,
      "shape_type": "rectangle",
      "flags": {},
      "attributes": {},
      "kie_linking": []
    },
    {
      "label": "blue",
      "score": 0.5727825164794922,
      "points": [
        [
          0.449615478515625,
          501.38153076171875
        ],
        [
          90.87571716308594,
          501.38153076171875
        ],
        [
          90.87571716308594,
          638.4054565429688
        ],
        [
          0.449615478515625,
          638.4054565429688
        ]
      ],
      "group_id": null,
      "description": null,
      "difficult": false,
      "shape_type": "rectangle",
      "flags": {},
      "attributes": {},
      "kie_linking": []
    }
  ],
  "imagePath": "../images/image_0416013654_20.png",
  "imageData": null,
  "imageHeight": 720,
  "imageWidth": 1280
}