{
  "version": "2.5.3",
  "flags": {},
  "shapes": [
    {
      "label": "blue",
      "score": 0.945244312286377,
      "points": [
        [
          152.09817504882812,
          542.7283935546875
        ],
        [
          320.3892517089844,
          542.7283935546875
        ],
        [
          320.3892517089844,
          702.832763671875
        ],
        [
          152.09817504882812,
          702.832763671875
        ]
      ],
      "group_id": null,
      "description": null,
      "difficult": false,
      "shape_type": "rectangle",
      "flags": {},
      "attributes": {},
      "kie_linking": []
    },
    {
      "label": "yellow",
      "score": 0.9408795833587646,
      "points": [
        [
          463.9797668457031,
          357.8800048828125
        ],
        [
          575.427734375,
          357.8800048828125
        ],
        [
          575.427734375,
          467.4185791015625
        ],
        [
          463.9797668457031,
          467.4185791015625
        ]
      ],
      "group_id": null,
      "description": null,
      "difficult": false,
      "shape_type": "rectangle",
      "flags": {},
      "attributes": {},
      "kie_linking": []
    },
    {
      "label": "black",
      "score": 0.9408364295959473,
      "points": [
        [
          748.1746826171875,
          273.18450927734375
        ],
        [
          834.9906005859375,
          273.18450927734375
        ],
        [
          834.9906005859375,
          364.80499267578125
        ],
        [
          748.1746826171875,
          364.80499267578125
        ]
      ],
      "group_id": null,
      "description": null,
      "difficult": false,
      "shape_type": "rectangle",
      "flags": {},
      "attributes": {},
      "kie_linking": []
    },
    {
      "label": "blue",
      "score": 0.9400067329406738,
      "points": [
        [
          275.52923583984375,
          405.4468994140625
        ],
        [
          405.2613525390625,
          405.4468994140625
        ],
        [
          405.2613525390625,
          530.5391845703125
        ],
        [
          275.52923583984375,
          530.5391845703125
        ]
      ],
      "group_id": null,
      "description": null,
      "difficult": false,
      "shape_type": "rectangle",
      "flags": {},
      "attributes": {},
      "kie_linking": []
    },
    {
      "label": "blue",
      "score": 0.9389111995697021,
      "points": [
        [
          632.5888671875,
          464.4072265625
        ],
        [
          764.30224609375,
          464.4072265625
        ],
        [
          764.30224609375,
          602.0001220703125
        ],
        [
          632.5888671875,
          602.0001220703125
        ]
      ],
      "group_id": null,
      "description": null,
      "difficult": false,
      "shape_type": "rectangle",
      "flags": {},
      "attributes": {},
      "kie_linking": []
    },
    {
      "label": "black",
      "score": 0.9343734979629517,
      "points": [
        [
          1143.523193359375,
          256.4989013671875
        ],
        [
          1240.768798828125,
          256.4989013671875
        ],
        [
          1240.768798828125,
          353.3035888671875
        ],
        [
          1143.523193359375,
          353.3035888671875
        ]
      ],
      "group_id": null,
      "description": null,
      "difficult": false,
      "shape_type": "rectangle",
      "flags": {},
      "attributes": {},
      "kie_linking": []
    },
    {
      "label": "red",
      "score": 0.9297254085540771,
      "points": [
        [
          812.3775024414062,
          185.07403564453125
        ],
        [
          881.4540405273438,
          185.07403564453125
        ],
        [
          881.4540405273438,
          252.00054931640625
        ],
        [
          812.3775024414062,
          252.00054931640625
        ]
      ],
      "group_id": null,
      "description": null,
      "difficult": false,
      "shape_type": "rectangle",
      "flags": {},
      "attributes": {},
      "kie_linking": []
    },
    {
      "label": "black",
      "score": 0.9292899370193481,
      "points": [
        [
          579.611083984375,
          195.34344482421875
        ],
        [
          648.5869140625,
          195.34344482421875
        ],
        [
          648.5869140625,
          273.04974365234375
        ],
        [
          579.611083984375,
          273.04974365234375
        ]
      ],
      "group_id": null,
      "description": null,
      "difficult": false,
      "shape_type": "rectangle",
      "flags": {},
      "attributes": {},
      "kie_linking": []
    },
    {
      "label": "blue",
      "score": 0.9137870073318481,
      "points": [
        [
          743.8779296875,
          223.884033203125
        ],
        [
          819.8778076171875,
          223.884033203125
        ],
        [
          819.8778076171875,
          304.644287109375
        ],
        [
          743.8779296875,
          304.644287109375
        ]
      ],
      "group_id": null,
      "description": null,
      "difficult": false,
      "shape_type": "rectangle",
      "flags": {},
      "attributes": {},
      "kie_linking": []
    },
    {
      "label": "red",
      "score": 0.8487207293510437,
      "points": [
        [
          0.0,
          531.5521240234375
        ],
        [
          91.92709350585938,
          531.5521240234375
        ],
        [
          91.92709350585938,
          687.4237060546875
        ],
        [
          0.0,
          687.4237060546875
        ]
      ],
      "group_id": null,
      "description": null,
      "difficult": false,
      "shape_type": "rectangle",
      "flags": {},
      "attributes": {},
      "kie_linking": []
    }
  ],
  "imagePath": "../images/image_0416013654_17.png",
  "imageData": null,
  "imageHeight": 720,
  "imageWidth": 1280
}